bootstrap_daterangepicker/__init__.py
bootstrap_daterangepicker/fields.py
bootstrap_daterangepicker/widgets.py
bootstrap_daterangepicker/templates/bootstrap_daterangepicker/daterangepicker.html
django4_bootstrap_daterangepicker-1.0.7.dist-info/LICENSE
django4_bootstrap_daterangepicker-1.0.7.dist-info/METADATA
django4_bootstrap_daterangepicker-1.0.7.dist-info/WHEEL
django4_bootstrap_daterangepicker-1.0.7.dist-info/top_level.txt
django4_bootstrap_daterangepicker-1.0.7.dist-info/RECORD
