Metadata-Version: 2.1
Name: django4-bootstrap-daterangepicker
Version: 1.0.7
Summary: A Django form field and widget wrapper for bootstrap-daterangepicker
Home-page: https://github.com/jckw/django-bootstrap-daterangepicker/
Author: Yuri Malinov, Jack Weatherilt, D
Author-email: yurik.m@gmail.com, jackweatherilt@outlook.com, protasov.d.51@gmail.com
License: MIT
Keywords: daterangepicker django4 django daterange datetime date bootstrap picker
Classifier: Development Status :: 4 - Beta
Classifier: Intended Audience :: Developers
Classifier: License :: OSI Approved :: MIT License
Classifier: Programming Language :: Python :: 3
Classifier: Operating System :: OS Independent
Classifier: Topic :: Software Development :: Libraries :: Python Modules
Classifier: Topic :: Utilities
Classifier: Environment :: Web Environment
Classifier: Framework :: Django :: 4.0
License-File: LICENSE
Requires-Dist: django
Requires-Dist: python-dateutil
Requires-Dist: six
